[
  {
    "name": "Hacktiv8",
    "type": "platinum",
    "logo": "Logo-Hacktiv8.png",
    "url": "https://hacktiv8.com/"
  },
  {
    "name": "Microsoft",
    "type": "platinum",
    "logo": "microsoft.png",
    "url": "https://www.microsoft.com/id-id/"
  },
  {
    "name": "Feedloop",
    "type": "silver",
    "logo": "feedloop.svg",
    "url": "https://feedloop.io/"
  },
  {
    "name": "HyperJump",
    "type": "silver",
    "logo": "hyperjump.png",
    "url": "https://www.linkedin.com/company/hyperjump/"
  },
  {
    "name": "bukalapak",
    "type": "silver",
    "logo": "bukalapak_new.png",
    "url": "https://jsday.id"
  },
  {
    "name": "qiscus",
    "type": "silver",
    "logo": "qiscus.svg",
    "url": "https://jsday.id"
  },
  {
    "name": "Shopee",
    "type": "gold",
    "logo": "shopee_new.png",
    "url": "https://shopee.co.id/"
  },
  {
    "name": "BRI",
    "type": "gold",
    "logo": "Logo_BRI.png",
    "url": "https://bri.co.id/"
  },
  {
    "name": "Warung Pintar",
    "type": "gold",
    "logo": "warung.png",
    "url": "https://warungpintar.co.id/"
  }
]
